{
    "program": [
        "$"
    ],
    "block": [
        "T_RCB"
    ],
    "declaration": [
        "T_INT",
        "T_BREAK",
        "T_CHAR",
        "T_FOR",
        "T_RCB",
        "T_VOID",
        "T_CONTINUE",
        "T_PRINT",
        "T_IF",
        "T_RETURN",
        "$",
        "T_BOOL",
        "T_ID"
    ],
    "dec'": [
        "T_INT",
        "T_BREAK",
        "T_CHAR",
        "T_FOR",
        "T_RCB",
        "T_VOID",
        "T_CONTINUE",
        "T_PRINT",
        "T_IF",
        "T_RETURN",
        "$",
        "T_BOOL",
        "T_ID"
    ],
    "dec''": [
        "T_INT",
        "T_BREAK",
        "T_CHAR",
        "T_FOR",
        "T_RCB",
        "T_VOID",
        "T_CONTINUE",
        "T_PRINT",
        "T_IF",
        "T_RETURN",
        "$",
        "T_BOOL",
        "T_ID"
    ],
    "v_dec": [],
    "stmt": [
        "T_INT",
        "T_BREAK",
        "T_CHAR",
        "T_FOR",
        "T_VOID",
        "T_CONTINUE",
        "T_PRINT",
        "T_IF",
        "T_RETURN",
        "T_BOOL",
        "T_ID"
    ],
    "stmt'": [
        "T_INT",
        "T_BREAK",
        "T_CHAR",
        "T_FOR",
        "T_VOID",
        "T_CONTINUE",
        "T_PRINT",
        "T_IF",
        "T_RETURN",
        "T_BOOL",
        "T_ID"
    ],
    "type": [
        "T_ID"
    ],
    "id_list": [
        "T_SEMICOLON"
    ],
    "id_list''": [
        "T_COMMA",
        "T_SEMICOLON"
    ],
    "argument_list": [
        "T_RP"
    ],
    "argument": [
        "T_COMMA",
        "T_RP"
    ],
    "id_name": [
        "T_ASSIGN",
        "T_COMMA",
        "T_SEMICOLON",
        "T_RP"
    ],
    "par_list": [
        "T_RP"
    ],
    "id_list'''": [
        "T_COMMA",
        "T_SEMICOLON"
    ],
    "for_init": [
        "T_SEMICOLON"
    ],
    "for_stmt": [
        "T_RP"
    ],
    "for_step": [
        "T_RP"
    ],
    "assign_expr": [
        "T_COMMA",
        "T_SEMICOLON",
        "T_RP"
    ],
    "for_cond": [
        "T_SEMICOLON"
    ],
    "comp_expr'": [
    ],
    "comp_expr": [
        "T_SEMICOLON",
        "T_RP"
    ],
    "return_stmt": [
        "T_SEMICOLON"
    ],
    "return_val": [
        "T_SEMICOLON"
    ],
    "expr": [
        "T_GE",
        "T_COMMA",
        "T_LT",
        "T_LE",
        "T_RSB",
        "T_NOT_EQUALS",
        "T_EQUALS",
        "T_GT",
        "T_RP",
        "T_SEMICOLON"
    ],
    "term": [
        "T_GE",
        "T_COMMA",
        "T_LT",
        "T_MINUS",
        "T_OR",
        "T_LE",
        "T_AND",
        "T_RSB",
        "T_NOT_EQUALS",
        "T_EQUALS",
        "T_GT",
        "T_RP",
        "T_SEMICOLON",
        "T_PLUS"
    ],
    "fact": [
        "T_GE",
        "T_COMMA",
        "T_LT",
        "T_MINUS",
        "T_OR",
        "T_LE",
        "T_MOD",
        "T_AND",
        "T_DIV",
        "T_RSB",
        "T_NOT_EQUALS",
        "T_EQUALS",
        "T_GT",
        "T_MULT",
        "T_RP",
        "T_SEMICOLON",
        "T_PLUS"
    ],
    "un_expr": [
        "T_GE",
        "T_COMMA",
        "T_LT",
        "T_MINUS",
        "T_OR",
        "T_LE",
        "T_MOD",
        "T_AND",
        "T_DIV",
        "T_RSB",
        "T_NOT_EQUALS",
        "T_EQUALS",
        "T_GT",
        "T_MULT",
        "T_RP",
        "T_SEMICOLON",
        "T_PLUS"
    ],
    "value": [
        "T_GE",
        "T_COMMA",
        "T_LT",
        "T_MINUS",
        "T_OR",
        "T_LE",
        "T_MOD",
        "T_AND",
        "T_DIV",
        "T_RSB",
        "T_NOT_EQUALS",
        "T_EQUALS",
        "T_GT",
        "T_MULT",
        "T_RP",
        "T_SEMICOLON",
        "T_PLUS"
    ],
    "value'": [
        "T_GE",
        "T_COMMA",
        "T_LT",
        "T_MINUS",
        "T_OR",
        "T_LE",
        "T_MOD",
        "T_AND",
        "T_DIV",
        "T_RSB",
        "T_NOT_EQUALS",
        "T_EQUALS",
        "T_GT",
        "T_MULT",
        "T_RP",
        "T_SEMICOLON",
        "T_PLUS"
    ],
    "id_name'": [
        "T_GE",
        "T_COMMA",
        "T_LT",
        "T_MINUS",
        "T_OR",
        "T_LE",
        "T_MOD",
        "T_AND",
        "T_DIV",
        "T_RSB",
        "T_NOT_EQUALS",
        "T_EQUALS",
        "T_GT",
        "T_MULT",
        "T_RP",
        "T_ASSIGN",
        "T_SEMICOLON",
        "T_PLUS"
    ],
    "id_list'": [
        "T_SEMICOLON"
    ],
    "func_call": [
        "T_GE",
        "T_COMMA",
        "T_LT",
        "T_MINUS",
        "T_OR",
        "T_LE",
        "T_MOD",
        "T_AND",
        "T_DIV",
        "T_RSB",
        "T_NOT_EQUALS",
        "T_EQUALS",
        "T_GT",
        "T_MULT",
        "T_RP",
        "T_SEMICOLON",
        "T_PLUS"
    ],
    "par_list'": [
        "T_RP"
    ],
    "expr'": [
        "T_GE",
        "T_COMMA",
        "T_LT",
        "T_LE",
        "T_RSB",
        "T_NOT_EQUALS",
        "T_EQUALS",
        "T_GT",
        "T_RP",
        "T_SEMICOLON"
    ],
    "term'": [
        "T_GE",
        "T_COMMA",
        "T_LT",
        "T_MINUS",
        "T_OR",
        "T_LE",
        "T_AND",
        "T_RSB",
        "T_NOT_EQUALS",
        "T_EQUALS",
        "T_GT",
        "T_RP",
        "T_SEMICOLON",
        "T_PLUS"
    ],
    "imm": [
        "T_GE",
        "T_COMMA",
        "T_LT",
        "T_MINUS",
        "T_OR",
        "T_LE",
        "T_MOD",
        "T_AND",
        "T_DIV",
        "T_RSB",
        "T_NOT_EQUALS",
        "T_EQUALS",
        "T_GT",
        "T_MULT",
        "T_RP",
        "T_SEMICOLON",
        "T_PLUS"
    ],
    "logic_imm": [
        "T_GE",
        "T_COMMA",
        "T_LT",
        "T_MINUS",
        "T_OR",
        "T_LE",
        "T_MOD",
        "T_AND",
        "T_DIV",
        "T_RSB",
        "T_NOT_EQUALS",
        "T_EQUALS",
        "T_GT",
        "T_MULT",
        "T_RP",
        "T_SEMICOLON",
        "T_PLUS"
    ],
    "low_bin_op": [
        "T_FALSE",
        "T_HEX_VAL",
        "T_DEC_VAL",
        "T_STR_VAL",
        "T_TRUE",
        "T_MINUS",
        "T_NOT",
        "T_LP",
        "T_PLUS",
        "T_CHAR_VAL",
        "T_ID"
    ],
    "high_bin_op": [
        "T_FALSE",
        "T_HEX_VAL",
        "T_DEC_VAL",
        "T_STR_VAL",
        "T_TRUE",
        "T_MINUS",
        "T_NOT",
        "T_LP",
        "T_PLUS",
        "T_CHAR_VAL",
        "T_ID"
    ],
    "un_op": [
        "T_FALSE",
        "T_HEX_VAL",
        "T_DEC_VAL",
        "T_STR_VAL",
        "T_TRUE",
        "T_CHAR_VAL",
        "T_ID"
    ],
    "block_expr": [
        "T_INT",
        "T_BREAK",
        "T_CHAR",
        "T_FOR",
        "T_VOID",
        "T_CONTINUE",
        "T_PRINT",
        "T_IF",
        "T_RETURN",
        "T_BOOL",
        "T_ID"
    ],
    "if_block": [
        "T_INT",
        "T_BREAK",
        "T_CHAR",
        "T_FOR",
        "T_VOID",
        "T_CONTINUE",
        "T_PRINT",
        "T_IF",
        "T_RETURN",
        "T_BOOL",
        "T_ID"
    ],
    "else_if_blocks": [
        "T_INT",
        "T_BREAK",
        "T_CHAR",
        "T_FOR",
        "T_VOID",
        "T_ELSE",
        "T_CONTINUE",
        "T_PRINT",
        "T_IF",
        "T_RETURN",
        "T_BOOL",
        "T_ID"
    ],
    "else_block": [
        "T_INT",
        "T_BREAK",
        "T_CHAR",
        "T_FOR",
        "T_VOID",
        "T_CONTINUE",
        "T_PRINT",
        "T_IF",
        "T_RETURN",
        "T_BOOL",
        "T_ID"
    ],
    "for_block": [
        "T_INT",
        "T_BREAK",
        "T_CHAR",
        "T_FOR",
        "T_VOID",
        "T_CONTINUE",
        "T_PRINT",
        "T_IF",
        "T_RETURN",
        "T_BOOL",
        "T_ID"
    ],
    "comp_bin_op": [
        "T_FALSE",
        "T_HEX_VAL",
        "T_DEC_VAL",
        "T_STR_VAL",
        "T_TRUE",
        "T_MINUS",
        "T_NOT",
        "T_LP",
        "T_PLUS",
        "T_CHAR_VAL",
        "T_ID"
    ],
    "func": [
        "T_INT",
        "T_BREAK",
        "T_CHAR",
        "T_FOR",
        "T_RCB",
        "T_VOID",
        "T_CONTINUE",
        "T_PRINT",
        "T_IF",
        "T_RETURN",
        "$",
        "T_BOOL",
        "T_ID"
    ],
    "argument_list'": [
        "T_RP"
    ]
}